main/__init__.py
main/example.py
main/tk_flow.py
tk_flow-0.0.0.dist-info/LICENSE
tk_flow-0.0.0.dist-info/METADATA
tk_flow-0.0.0.dist-info/WHEEL
tk_flow-0.0.0.dist-info/top_level.txt
tk_flow-0.0.0.dist-info/RECORD
