Metadata-Version: 2.1
Name: tk-flow
Version: 0.0.0
Summary: Using the tkinter UI library to build flowcharts.
Author-email: Alex Cecil <ajcecil@iastate.edu>
Maintainer-email: Alex Cecil <ajcecil@iastate.edu>
License: MIT License
Project-URL: Repository, https://github.com/ajcecil/tk_flow.git
Keywords: flowchart,flow,flowcharts,charts
Classifier: Development Status :: 5 - Production/Stable
Classifier: Programming Language :: Python
Requires-Python: >=3.6
License-File: LICENSE
